{
  "version": 1,
  "sessionId": "0481e7cb-0ae6-43bc-a6b5-73906f4ce643",
  "status": "running",
  "startedAt": "2026-03-16T09:03:06.730Z",
  "updatedAt": "2026-03-16T09:30:52.088Z",
  "currentIteration": 0,
  "maxIterations": 10,
  "tasksCompleted": 0,
  "isPaused": false,
  "agentPlugin": "gemini",
  "trackerState": {
    "plugin": "json",
    "prdPath": "./tasks/prd.json",
    "totalTasks": 6,
    "tasks": [
      {
        "id": "US-001",
        "title": "自动监听与群组过滤",
        "status": "open",
        "completedInSession": false
      },
      {
        "id": "US-002",
        "title": "表情包与元数据直接过滤",
        "status": "open",
        "completedInSession": false
      },
      {
        "id": "US-003",
        "title": "视觉大模型 (VLM) 结构化分析",
        "status": "open",
        "completedInSession": false
      },
      {
        "id": "US-004",
        "title": "图像持久化与 SQLite 记录",
        "status": "open",
        "completedInSession": false
      },
      {
        "id": "US-005",
        "title": "标签检索交互指令",
        "status": "open",
        "completedInSession": false
      },
      {
        "id": "US-006",
        "title": "数据库统计面板展示",
        "status": "open",
        "completedInSession": false
      }
    ]
  },
  "iterations": [],
  "skippedTaskIds": [],
  "cwd": "C:\\Users\\Administrator\\test-project\\AstrBot\\data\\plugins\\astrbot_plugin_collectimage",
  "activeTaskIds": [],
  "subagentPanelVisible": false
}